{
  "cookies": [
    {
      "name": "wordpress_sec_bcee46caf8128c4169fb42a56c1b36e7",
      "value": "practiceuser1%7C1695662223%7CUL4dOm1mYwca03YUU1Dza619ZhZ5XwKNibMFWDW2qjs%7Cec68e10f29e4654261b50c03f780bf80ddd22055c886f133fed9cb713aa446fb",
      "domain": "practice.sdetunicorns.com",
      "path": "/wp-content/plugins",
      "expires": -1,
      "httpOnly": true,
      "secure": true,
      "sameSite": "None"
    },
    {
      "name": "wordpress_sec_bcee46caf8128c4169fb42a56c1b36e7",
      "value": "practiceuser1%7C1695662223%7CUL4dOm1mYwca03YUU1Dza619ZhZ5XwKNibMFWDW2qjs%7Cec68e10f29e4654261b50c03f780bf80ddd22055c886f133fed9cb713aa446fb",
      "domain": "practice.sdetunicorns.com",
      "path": "/wp-admin",
      "expires": -1,
      "httpOnly": true,
      "secure": true,
      "sameSite": "None"
    },
    {
      "name": "wp_wpfileupload_bcee46caf8128c4169fb42a56c1b36e7",
      "value": "wDLcEzaAOQNMS328PxeDQW6LpPcQ6srN",
      "domain": "practice.sdetunicorns.com",
      "path": "/",
      "expires": 1695662219.88994,
      "httpOnly": false,
      "secure": false,
      "sameSite": "Lax"
    },
    {
      "name": "tk_or",
      "value": "%22%22",
      "domain": ".sdetunicorns.com",
      "path": "/",
      "expires": 1730049423.132938,
      "httpOnly": false,
      "secure": false,
      "sameSite": "Lax"
    },
    {
      "name": "tk_r3d",
      "value": "%22%22",
      "domain": ".sdetunicorns.com",
      "path": "/",
      "expires": 1695748623,
      "httpOnly": false,
      "secure": false,
      "sameSite": "Lax"
    },
    {
      "name": "tk_lr",
      "value": "%22%22",
      "domain": ".sdetunicorns.com",
      "path": "/",
      "expires": 1727025423,
      "httpOnly": false,
      "secure": false,
      "sameSite": "Lax"
    },
    {
      "name": "wordpress_logged_in_bcee46caf8128c4169fb42a56c1b36e7",
      "value": "practiceuser1%7C1695662223%7CUL4dOm1mYwca03YUU1Dza619ZhZ5XwKNibMFWDW2qjs%7Caab1f0f631987edd156ed51d052c06eb620837670ec85eb73daeb43a804f31ac",
      "domain": "practice.sdetunicorns.com",
      "path": "/",
      "expires": -1,
      "httpOnly": true,
      "secure": false,
      "sameSite": "Lax"
    },
    {
      "name": "woocommerce_items_in_cart",
      "value": "1",
      "domain": "practice.sdetunicorns.com",
      "path": "/",
      "expires": -1,
      "httpOnly": false,
      "secure": false,
      "sameSite": "Lax"
    },
    {
      "name": "woocommerce_cart_hash",
      "value": "6b4f5128aced7ce3ea1d0fab860bc584",
      "domain": "practice.sdetunicorns.com",
      "path": "/",
      "expires": -1,
      "httpOnly": false,
      "secure": false,
      "sameSite": "Lax"
    },
    {
      "name": "wp_woocommerce_session_bcee46caf8128c4169fb42a56c1b36e7",
      "value": "175%7C%7C1695662223%7C%7C1695658623%7C%7Ca33cc12623e12b3cda12e4a5a506c260",
      "domain": "practice.sdetunicorns.com",
      "path": "/",
      "expires": 1695662225.122103,
      "httpOnly": true,
      "secure": false,
      "sameSite": "Lax"
    }
  ],
  "origins": []
}